{
    "configurations": [
        {
            "name": "Mac",
            "includePath": [
                "/usr/include",
                "/usr/local/include",
                "/opt/ros/kinetic/include",
                "../devel/include",
                "${workspaceRoot}",
                "/home/daniele/work/workspace_cpp/SitecoLadybugTools/SitecoLadybugTools/include"
            ],
            "browse": {
                "limitSymbolsToIncludedHeaders": true,
                "databaseFilename": "",
                "path": [
                    "/usr/include",
                    "/usr/local/include",
                    "/opt/ros/kinetic/include",
                    "../devel/include",
                    "${workspaceRoot}"
                ]
            },
            "intelliSenseMode": "clang-x64",
            "macFrameworkPath": [
                "/System/Library/Frameworks",
                "/Library/Frameworks"
            ]
        },
        {
            "name": "Linux",
            "includePath": [
                "/usr/include",
                "/usr/local/include",
                "/opt/ros/kinetic/include",
                "../devel/include",
                "${workspaceRoot}",
                "/opt/ros/kinetic/include/opencv-3.3.1-dev",
                "/usr/include/eigen3",
                "${workspaceFolder}/include",
                "/home/daniele/work/workspace_cpp/SitecoLadybugTools/SitecoLadybugTools/include"
            ],
            "browse": {
                "limitSymbolsToIncludedHeaders": true,
                "databaseFilename": "",
                "path": [
                    "/usr/include",
                    "/usr/local/include",
                    "/opt/ros/kinetic/include",
                    "../devel/include",
                    "${workspaceRoot}",
                    "/home/daniele/work/workspace_cpp/SitecoLadybugTools/SitecoLadybugTools/include"
                ]
            },
            "intelliSenseMode": "clang-x64",
            "compilerPath": "/usr/bin/gcc",
            "cStandard": "c11",
            "cppStandard": "c++17"
        },
        {
            "name": "Win32",
            "includePath": [
                "C:/Program Files (x86)/Microsoft Visual Studio 14.0/VC/include/*",
                "${workspaceRoot}"
            ],
            "browse": {
                "limitSymbolsToIncludedHeaders": true,
                "databaseFilename": "",
                "path": [
                    "C:/Program Files (x86)/Microsoft Visual Studio 14.0/VC/include/*",
                    "${workspaceRoot}"
                ]
            },
            "intelliSenseMode": "msvc-x64"
        }
    ],
    "version": 4
}